base/__init__.py
base/admin.py
base/apps.py
base/models.py
base/signals.py
base/urls.py
base/validators.py
base/views.py
base_user/__init__.py
base_user/admin.py
base_user/apps.py
base_user/managers.py
base_user/models.py
base_user/serializers.py
base_user/tests.py
base_user/utils.py
base_user/views.py
base_user/migrations/0001_initial.py
base_user/migrations/__init__.py
django_firebase_mcp/__init__.py
django_firebase_mcp/asgi.py
django_firebase_mcp/settings.py
django_firebase_mcp/urls.py
django_firebase_mcp/wsgi.py
django_firebase_mcp-0.0.2.dist-info/licenses/LICENSE.txt
firebase_admin_mcp/__init__.py
firebase_admin_mcp/admin.py
firebase_admin_mcp/apps.py
firebase_admin_mcp/demo_standalone_agent.py
firebase_admin_mcp/firebase_init.py
firebase_admin_mcp/models.py
firebase_admin_mcp/standalone_firebase_agent.py
firebase_admin_mcp/tests.py
firebase_admin_mcp/urls.py
firebase_admin_mcp/views.py
firebase_admin_mcp/management/__init__.py
firebase_admin_mcp/management/commands/__init__.py
firebase_admin_mcp/management/commands/run_mcp.py
firebase_admin_mcp/migrations/__init__.py
firebase_admin_mcp/tests/__init__.py
firebase_admin_mcp/tests/demo_firebase_mcp.py
firebase_admin_mcp/tests/final_mcp_test.py
firebase_admin_mcp/tests/run_mcp_test.py
firebase_admin_mcp/tests/test_firebase_connection.py
firebase_admin_mcp/tests/test_firestore.py
firebase_admin_mcp/tests/test_mcp_complete.py
firebase_admin_mcp/tests/test_mcp_firestore_complete.py
firebase_admin_mcp/tests/test_mcp_http.py
firebase_admin_mcp/tests/test_mcp_tools.py
firebase_admin_mcp/tests/test_simple_firestore.py
firebase_admin_mcp/tests/test_sync_firestore.py
firebase_admin_mcp/tests/test_tools.py
firebase_admin_mcp/tools/__init__.py
firebase_admin_mcp/tools/auth.py
firebase_admin_mcp/tools/firestore.py
firebase_admin_mcp/tools/storage.py
django_firebase_mcp-0.0.2.dist-info/METADATA
django_firebase_mcp-0.0.2.dist-info/WHEEL
django_firebase_mcp-0.0.2.dist-info/top_level.txt
django_firebase_mcp-0.0.2.dist-info/RECORD
