Metadata-Version: 2.4
Name: django-firebase-mcp
Version: 0.0.2
Summary: A production-ready Django app implementing Firebase Model Context Protocol (MCP) server with 14 Firebase tools for AI agents. Features standalone agent, HTTP/stdio transport, LangChain integration, and complete Firebase service coverage (Auth, Firestore, Storage).
Home-page: https://github.com/raghavdasila/django-firebase-mcp
Author: Raghvendra Dasila
Author-email: raghavdasila@gmail.com
License: MIT
Classifier: Development Status :: 3 - Alpha
Classifier: Framework :: Django
Classifier: Intended Audience :: Developers
Classifier: Topic :: Software Development :: Libraries :: Python Modules
Classifier: Programming Language :: Python :: 3
Classifier: Programming Language :: Python :: 3.10
Classifier: License :: OSI Approved :: MIT License
Classifier: Operating System :: OS Independent
Requires-Python: >=3.10
License-File: LICENSE.txt
Dynamic: author
Dynamic: author-email
Dynamic: classifier
Dynamic: description
Dynamic: description-content-type
Dynamic: home-page
Dynamic: license
Dynamic: license-file
Dynamic: requires-python
Dynamic: summary
